{"errors":[],"warnings":[],"namedChunkGroups":{"app":{"chunks":[6,5,2],"assets":["webpack-runtime-0643ab8b6f8b7285a98c.js","webpack-runtime-0643ab8b6f8b7285a98c.js.map","framework-d9cf0f47b747b267fae2.js","framework-d9cf0f47b747b267fae2.js.map","app-e5d903b08050d4ce5197.js","app-e5d903b08050d4ce5197.js.map"],"children":{},"childAssets":{}},"component---src-pages-404-js":{"chunks":[1,0,3],"assets":["styles.3136d31c15cca307b1bb.css","styles-c2fe8482057191dca484.js","styles-c2fe8482057191dca484.js.map","commons-d0560a310ae27b853895.js","commons-d0560a310ae27b853895.js.map","component---src-pages-404-js-f23be3c941dcfac6ae88.js","component---src-pages-404-js-f23be3c941dcfac6ae88.js.map"],"children":{},"childAssets":{}},"component---src-pages-index-js":{"chunks":[1,0,4],"assets":["styles.3136d31c15cca307b1bb.css","styles-c2fe8482057191dca484.js","styles-c2fe8482057191dca484.js.map","commons-d0560a310ae27b853895.js","commons-d0560a310ae27b853895.js.map","component---src-pages-index-js-f8e2c6807c1feab14f51.js","component---src-pages-index-js-f8e2c6807c1feab14f51.js.map"],"children":{},"childAssets":{}}},"assetsByChunkName":{"app":["webpack-runtime-0643ab8b6f8b7285a98c.js","framework-d9cf0f47b747b267fae2.js","app-e5d903b08050d4ce5197.js"],"component---src-pages-404-js":["styles.3136d31c15cca307b1bb.css","styles-c2fe8482057191dca484.js","commons-d0560a310ae27b853895.js","component---src-pages-404-js-f23be3c941dcfac6ae88.js"],"component---src-pages-index-js":["styles.3136d31c15cca307b1bb.css","styles-c2fe8482057191dca484.js","commons-d0560a310ae27b853895.js","component---src-pages-index-js-f8e2c6807c1feab14f51.js"]}}